hologram/__init__.py
hologram/claude_cognitive.py
hologram/cli.py
hologram/coordinates.py
hologram/crystallize.py
hologram/dag.py
hologram/hooks.py
hologram/pressure.py
hologram/resolution.py
hologram/router.py
hologram/session.py
hologram/system.py
hologram/turn_state.py
hologram_cognitive-0.3.3.dist-info/METADATA
hologram_cognitive-0.3.3.dist-info/WHEEL
hologram_cognitive-0.3.3.dist-info/entry_points.txt
hologram_cognitive-0.3.3.dist-info/licenses/LICENSE
hologram_cognitive-0.3.3.dist-info/RECORD
