Metadata-Version: 2.4
Name: hologram-cognitive
Version: 0.3.3
Summary: Pressure-based context routing with attention basins and lighthouse resurrection for LLMs
Project-URL: Homepage, https://github.com/mirrorethic/hologram-cognitive
Project-URL: Documentation, https://github.com/mirrorethic/hologram-cognitive#readme
Project-URL: Repository, https://github.com/mirrorethic/hologram-cognitive
Project-URL: Issues, https://github.com/mirrorethic/hologram-cognitive/issues
Author-email: Garret Sutherland <gsutherland@mirrorethic.com>
License-Expression: MIT
License-File: LICENSE
Keywords: ai,attention,basin,claude,cognitive,context,crystallization,dag,llm,memory,pressure,routing
Classifier: Development Status :: 4 - Beta
Classifier: Intended Audience :: Developers
Classifier: License :: OSI Approved :: MIT License
Classifier: Programming Language :: Python :: 3
Classifier: Programming Language :: Python :: 3.9
Classifier: Programming Language :: Python :: 3.10
Classifier: Programming Language :: Python :: 3.11
Classifier: Programming Language :: Python :: 3.12
Classifier: Topic :: Scientific/Engineering :: Artificial Intelligence
Classifier: Topic :: Software Development :: Libraries :: Python Modules
Requires-Python: >=3.9
Provides-Extra: dev
Requires-Dist: black>=23.0; extra == 'dev'
Requires-Dist: pytest-cov>=4.0; extra == 'dev'
Requires-Dist: pytest>=7.0; extra == 'dev'
Requires-Dist: ruff>=0.1.0; extra == 'dev'
